yarrrml_translator/__init__.py
yarrrml_translator/__main__.py
yarrrml_translator/constants.py
yarrrml_translator/function.py
yarrrml_translator/graph.py
yarrrml_translator/mapping.py
yarrrml_translator/predicateobject.py
yarrrml_translator/source.py
yarrrml_translator/subject.py
yarrrml_translator/target.py
yarrrml_translator/termmap.py
yarrrml_translator-1.0.dist-info/METADATA
yarrrml_translator-1.0.dist-info/WHEEL
yarrrml_translator-1.0.dist-info/top_level.txt
yarrrml_translator-1.0.dist-info/RECORD
