Metadata-Version: 2.1
Name: yarrrml-translator
Version: 1.0
Summary: A translator from YARRRML to RML mappings.
Home-page: https://github.com/oeg-upm/yarrrml-translator
Author: David Chaves-Fraga
Author-email: david.chaves@upm.es
License: Apache 2.0
Project-URL: Source code, https://github.com/oeg-upm/yarrrml-translator
Project-URL: Issue tracker, https://github.com/oeg-upm/yarrrml-translator/issues
Classifier: Programming Language :: Python :: 3
Classifier: License :: OSI Approved :: Apache Software License
Classifier: Operating System :: OS Independent
Classifier: Environment :: Console
Classifier: Intended Audience :: Information Technology
Classifier: Topic :: Utilities
Classifier: Topic :: Software Development :: Pre-processors
Classifier: Topic :: Scientific/Engineering :: Interface Engine/Protocol Translator
Requires-Python: >=3.7
Requires-Dist: ruamel.yaml (>=0.17.21)
Requires-Dist: rdflib (>=6.2.0)
Requires-Dist: coloredlogs (>=15.0.1)
